artemis2tumonline/__init__.py
artemis2tumonline/main.py
artemis2tumonline/model/__init__.py
artemis2tumonline/model/artemis_entry.py
artemis2tumonline/model/tum_online_entry.py
artemis2tumonline-0.1.9.dist-info/entry_points.txt
artemis2tumonline-0.1.9.dist-info/LICENSE
artemis2tumonline-0.1.9.dist-info/WHEEL
artemis2tumonline-0.1.9.dist-info/METADATA
artemis2tumonline-0.1.9.dist-info/RECORD
