Metadata-Version: 2.1
Name: artemis2tumonline
Version: 0.1.9
Summary: 
Home-page: https://github.com/pstoeckle/artemis2tumonline.git
Author: Patrick Stöckle
Author-email: patrick.stoeckle@tum.de
Maintainer: Patrick Stöckle
Maintainer-email: patrick.stoeckle@tum.de
Requires-Python: >=3.8,<4.0
Classifier: Programming Language :: Python :: 3
Classifier: Programming Language :: Python :: 3.8
Classifier: Programming Language :: Python :: 3.9
Classifier: Programming Language :: Python :: 3.10
Requires-Dist: requests (>=2.28.1,<3.0.0)
Requires-Dist: typer (>=0.7.0,<0.8.0)
Project-URL: Repository, https://github.com/pstoeckle/artemis2tumonline.git
